PyEzFile/__init__.py
PyEzFile-0.0.2.dist-info/LICENSE
PyEzFile-0.0.2.dist-info/METADATA
PyEzFile-0.0.2.dist-info/WHEEL
PyEzFile-0.0.2.dist-info/top_level.txt
PyEzFile-0.0.2.dist-info/RECORD
