Metadata-Version: 2.1
Name: PyEzFile
Version: 0.0.2
Summary: Libreria para manejar archivos de forma mas sencilla
Home-page: https://github.com/shinraxor
Author: Pedro Lamarca
Author-email: pedro.lamarca.1997@gmail.com
License: MIT
Platform: UNKNOWN
License-File: LICENSE
